hackthederivative/__init__.py
hackthederivative-0.0.1.dist-info/DESCRIPTION.rst
hackthederivative-0.0.1.dist-info/METADATA
hackthederivative-0.0.1.dist-info/metadata.json
hackthederivative-0.0.1.dist-info/RECORD
hackthederivative-0.0.1.dist-info/top_level.txt
hackthederivative-0.0.1.dist-info/WHEEL
